{"id": 23444, "aliases": [29165], "name": "LATTICE 3X6 MODULE W/KNOBS", "no_image": false, "size": [5, 3, 1], "weight": 36.315918, "is_surplus": true, "n_usage": -1, "sources": [], "usage": ["BoomerWagon_VC000", "BurgerCar_VC000", "BurgerCar_VC001", "CarlaOffroad_VC000", "ClutchOffroad_VC000", "Clydesdale_VC000", "DrillTruck_60121", "Duhkar_VC000", "DumpCart_60124", "DuneBuggy_60173", "FirstClass_VC000", "ServiceCar_60351", "SpaceRoverExplorer_VC31107", "SUV_60149", "Traffic_FV_02Offroad", "Traffic_FV_05Offroad", "Truck_60121"]}