{"id": 2877, "aliases": [], "name": "PROFILE BRICK 1X2", "no_image": false, "size": [2, 1, 3], "weight": 20.751953, "is_surplus": false, "n_usage": -1, "sources": [], "usage": ["ApocalypseTruck_LU000", "Bajambug_VC000", "BalloonCar_VC000", "BigOlTexasTruck_VC000", "BigOlTexasTruck_VC002", "Bus_8404", "BuzzosRoyalBarge_VC000", "Camper_60057", "CatDeVille_VC000", "CatT_VC000", "CleaningTruck_60317", "DrinksTruck_60384", "DuneBuggy_60145", "Excavator_60152", "FastroBoat_VC000", "FastroStreet_VC000", "FireEngine_60002", "FireEngine_7891", "FireInflatable_7213", "FishingBoat_VC70442", "FishingBoat_70442", "FoodTruckA_VC000", "FoulRunningsBoat_VC000", "FoulRunningsStreet_VC000", "FoulRunningsTruck_VC000", "FusionOffroad_VC000", "GoldDrillerStreet_VC000", "GoldDrillerTruck_VC000", "GothaPlaneBoat_VC000", "GothaPlaneCar_VC000", "GothaPlaneTruck_VC000", "GreenCruiserBoat_31056", "GreenCruiserStreetCar_31056", "GreenCruiserTruck_VC31056", "GWP_Boat_VC000", "GWP_Street_VC000", "GWP_Truck_VC000", "HolidayCamperVan_60283", "HotGarbageStreet_VC000", "Hydro_VC001", "Hydro_31072", "HyperSpeed_VC60389A", "IceCreamTruckPoliceChase_60314B", "LightningBug_VC000", "MachioWidebody_VC000", "MoneyTransport_60142", "MonsterSchoolBus_LU000", "MonsterTruck_VC000", "MonsterTruck_60027", "Mower_7637", "OrganDonorStreet_VC000", "OrganDonorTruck_VC000", "PoliceK9Van_4441", "PoliceTruckQuestReward_VC000", "PoliceTruckQuest_VC000", "PoliceTruck_60007", "RaceCar_60383", "RaceyMcRaceFaceStreet_VC000", "RivalMadScientistStreetCar_VC0000", "Roadster_10200B", "Roadster_31072", "Roadster_9465", "ScienceBuggy_VC000", "ScienceBuggy_7312", "ServiceCar_60351", "ShadowMinionBoat", "SimpleBigRig_6340", "SimpleTowTruck_6397", "SpaceRoverExplorer_VC31107", "Speedboat_60221", "StreetSweeper_60152", "StreetSweeper_7242", "SuperBoat_60114", "SuperF1Racer_31072", "SwampBoat_VC000", "SwampBoat_5866", "TheBoxSetStreet_VC000", "TourBus_60200", "TowTruck_10264", "Tractor_7634", "TrainBoat_VC000", "TrainBoat_VC001", "UFO_Boat_VC000", "UtilityTruck_60152", "VampHearse_9464", "VeroVolt_Street_VC000"]}